habushu_mixology/__init__.py
habushu_mixology/generated/__init__.py
habushu_mixology/helloworld.py
habushu_mixology/reusable_module/__init__.py
habushu_mixology/reusable_module/worker.py
habushu_mixology/util/__init__.py
habushu_mixology/util/useful.py
habushu_mixology-2.7.0.dev1692701397.dist-info/METADATA
habushu_mixology-2.7.0.dev1692701397.dist-info/WHEEL
habushu_mixology-2.7.0.dev1692701397.dist-info/RECORD
